LICENSE.txt
MANIFEST.in
README.md
setup.py
/tmp/workspace/onfluent-kafka-python_2.4.0-beta/LICENSE.txt
/tmp/workspace/onfluent-kafka-python_2.4.0-beta/src/confluent_kafka/src/Admin.c
/tmp/workspace/onfluent-kafka-python_2.4.0-beta/src/confluent_kafka/src/AdminTypes.c
/tmp/workspace/onfluent-kafka-python_2.4.0-beta/src/confluent_kafka/src/Consumer.c
/tmp/workspace/onfluent-kafka-python_2.4.0-beta/src/confluent_kafka/src/Metadata.c
/tmp/workspace/onfluent-kafka-python_2.4.0-beta/src/confluent_kafka/src/Producer.c
/tmp/workspace/onfluent-kafka-python_2.4.0-beta/src/confluent_kafka/src/confluent_kafka.c
src/confluent_kafka/__init__.py
src/confluent_kafka/deserializing_consumer.py
src/confluent_kafka/error.py
src/confluent_kafka/serializing_producer.py
src/confluent_kafka/superstream_consumer.py
src/confluent_kafka/superstream_producer.py
src/confluent_kafka/_model/__init__.py
src/confluent_kafka/_util/__init__.py
src/confluent_kafka/_util/conversion_util.py
src/confluent_kafka/_util/validation_util.py
src/confluent_kafka/admin/__init__.py
src/confluent_kafka/admin/_acl.py
src/confluent_kafka/admin/_cluster.py
src/confluent_kafka/admin/_config.py
src/confluent_kafka/admin/_group.py
src/confluent_kafka/admin/_listoffsets.py
src/confluent_kafka/admin/_metadata.py
src/confluent_kafka/admin/_resource.py
src/confluent_kafka/admin/_scram.py
src/confluent_kafka/admin/_topic.py
src/confluent_kafka/avro/__init__.py
src/confluent_kafka/avro/cached_schema_registry_client.py
src/confluent_kafka/avro/error.py
src/confluent_kafka/avro/load.py
src/confluent_kafka/avro/serializer/__init__.py
src/confluent_kafka/avro/serializer/message_serializer.py
src/confluent_kafka/kafkatest/__init__.py
src/confluent_kafka/kafkatest/verifiable_client.py
src/confluent_kafka/kafkatest/verifiable_consumer.py
src/confluent_kafka/kafkatest/verifiable_producer.py
src/confluent_kafka/schema_registry/__init__.py
src/confluent_kafka/schema_registry/avro.py
src/confluent_kafka/schema_registry/error.py
src/superstream_confluent_kafka_test_beta.egg-info/PKG-INFO
src/superstream_confluent_kafka_test_beta.egg-info/SOURCES.txt
src/superstream_confluent_kafka_test_beta.egg-info/dependency_links.txt
src/superstream_confluent_kafka_test_beta.egg-info/requires.txt
src/superstream_confluent_kafka_test_beta.egg-info/top_level.txt