Metadata-Version: 2.1
Name: superstream-confluent-kafka-test-beta
Version: 2.4.0b0
Summary: Confluent's Python client for Apache Kafka
Home-page: https://github.com/superstreamlabs/confluent-kafka-python.git
Author: Superstream Labs
Author-email: support@superstream.ai
Classifier: Development Status :: 5 - Production/Stable
Classifier: Intended Audience :: Developers
Classifier: License :: OSI Approved :: Apache Software License
Classifier: Programming Language :: Python
Classifier: Programming Language :: Python :: 2.7
Classifier: Programming Language :: Python :: 3
Classifier: Topic :: Software Development :: Libraries :: Python Modules
Provides-Extra: schema-registry
Provides-Extra: avro
Provides-Extra: json
Provides-Extra: protobuf
Provides-Extra: dev
Provides-Extra: doc
License-File: LICENSE.txt
